src/__init__.py
src/config.py
src/cli/__init__.py
src/cli/auth_commands.py
src/cli/cache_commands.py
src/cli/common.py
src/cli/playlist_commands.py
src/core/__init__.py
src/core/auth.py
src/core/cache.py
src/core/sorting.py
src/core/youtube_api.py
src/output/__init__.py
src/output/formatters.py
src/types/__init__.py
src/types/youtube.py
ytplay-2.1.1.dist-info/METADATA
ytplay-2.1.1.dist-info/WHEEL
ytplay-2.1.1.dist-info/entry_points.txt
ytplay-2.1.1.dist-info/licenses/LICENSE.md
ytplay-2.1.1.dist-info/RECORD
