Metadata-Version: 2.4
Name: ytplay
Version: 2.1.1
Summary: A Python CLI tool to interact with the YouTube API and mainly to manage and sort playlists
License-File: LICENSE.md
Requires-Python: >=3.13
Requires-Dist: click>=8.2.1
Requires-Dist: google-api-python-client>=2.178.0
Requires-Dist: google-auth-httplib2>=0.2.0
Requires-Dist: google-auth-oauthlib>=1.2.2
Requires-Dist: tqdm>=4.67.1
